donzo_divide/__init__.py
donzo_divide/cal_divide.py
donzo_divide-0.1.1.dist-info/METADATA
donzo_divide-0.1.1.dist-info/WHEEL
donzo_divide-0.1.1.dist-info/entry_points.txt
donzo_divide-0.1.1.dist-info/top_level.txt
donzo_divide-0.1.1.dist-info/RECORD
